odoo/addons/sale_order_general_discount_triple/README.rst
odoo/addons/sale_order_general_discount_triple/__init__.py
odoo/addons/sale_order_general_discount_triple/__manifest__.py
odoo/addons/sale_order_general_discount_triple/i18n/it.po
odoo/addons/sale_order_general_discount_triple/i18n/sale_order_general_discount_triple.pot
odoo/addons/sale_order_general_discount_triple/models/__init__.py
odoo/addons/sale_order_general_discount_triple/models/res_config_settings.py
odoo/addons/sale_order_general_discount_triple/models/sale_order.py
odoo/addons/sale_order_general_discount_triple/models/sale_order_line.py
odoo/addons/sale_order_general_discount_triple/readme/CONTRIBUTORS.rst
odoo/addons/sale_order_general_discount_triple/readme/DESCRIPTION.rst
odoo/addons/sale_order_general_discount_triple/readme/HISTORY.rst
odoo/addons/sale_order_general_discount_triple/readme/USAGE.rst
odoo/addons/sale_order_general_discount_triple/static/description/icon.png
odoo/addons/sale_order_general_discount_triple/static/description/index.html
odoo/addons/sale_order_general_discount_triple/tests/__init__.py
odoo/addons/sale_order_general_discount_triple/tests/test_module.py
odoo/addons/sale_order_general_discount_triple/views/res_config_settings.xml
odoo14_addon_sale_order_general_discount_triple-14.0.2.0.1.dist-info/METADATA
odoo14_addon_sale_order_general_discount_triple-14.0.2.0.1.dist-info/WHEEL
odoo14_addon_sale_order_general_discount_triple-14.0.2.0.1.dist-info/top_level.txt
odoo14_addon_sale_order_general_discount_triple-14.0.2.0.1.dist-info/RECORD
